{
  "source": "images/X51005447851.jpg",
  "line_count": 40,
  "avg_confidence": 0.9689,
  "lines": [
    {
      "text": "PASARAYA BORONG PINTAR",
      "confidence": 0.9676
    },
    {
      "text": "SDN BHD",
      "confidence": 0.9462
    },
    {
      "text": "BRNo.124525-H",
      "confidence": 0.9813
    },
    {
      "text": "NO19-G&19-1&19-2JALAN TASIKUTAMA 4",
      "confidence": 0.9581
    },
    {
      "text": "MEDAN NIAGA TASIK DAMAI",
      "confidence": 0.9524
    },
    {
      "text": "016-5498845",
      "confidence": 0.992
    },
    {
      "text": "GST No.",
      "confidence": 0.9172
    },
    {
      "text": "30/01/201814:48:23",
      "confidence": 0.9622
    },
    {
      "text": "TAXINVOICE",
      "confidence": 0.9971
    },
    {
      "text": "TRN:CR0002815",
      "confidence": 0.9742
    },
    {
      "text": "COUNTER3",
      "confidence": 0.986
    },
    {
      "text": "CASHIER:11",
      "confidence": 0.9597
    },
    {
      "text": "QTYUOM",
      "confidence": 0.9925
    },
    {
      "text": "UNITAmt Exc Amt Inc.GST",
      "confidence": 0.9343
    },
    {
      "text": "Price",
      "confidence": 0.9988
    },
    {
      "text": "Tax",
      "confidence": 0.9956
    },
    {
      "text": "Tax Code",
      "confidence": 0.9548
    },
    {
      "text": "REVIVE 500ML",
      "confidence": 0.9329
    },
    {
      "text": "WALK",
      "confidence": 0.9861
    },
    {
      "text": "1.70",
      "confidence": 0.9997
    },
    {
      "text": "1.70",
      "confidence": 0.9994
    },
    {
      "text": "1.70 ZRL",
      "confidence": 0.9755
    },
    {
      "text": "TotalQty1.00",
      "confidence": 0.9708
    },
    {
      "text": "1.70",
      "confidence": 0.9975
    },
    {
      "text": "Total Includes GsT 0%",
      "confidence": 0.903
    },
    {
      "text": "1.70",
      "confidence": 0.9933
    },
    {
      "text": "Customer's Payment",
      "confidence": 0.9765
    },
    {
      "text": "Cash",
      "confidence": 0.998
    },
    {
      "text": "100.00",
      "confidence": 0.9993
    },
    {
      "text": "Change",
      "confidence": 0.9989
    },
    {
      "text": "98.30",
      "confidence": 0.9997
    },
    {
      "text": "GST Summary",
      "confidence": 0.9649
    },
    {
      "text": "Amount (RM)",
      "confidence": 0.9445
    },
    {
      "text": "Tax (RM)",
      "confidence": 0.9036
    },
    {
      "text": "ZRL=0%",
      "confidence": 0.951
    },
    {
      "text": "1.70",
      "confidence": 0.977
    },
    {
      "text": "0.00",
      "confidence": 0.9971
    },
    {
      "text": "*Goods sold are not returnable",
      "confidence": 0.9202
    },
    {
      "text": "Thank you for shopping at PASARAYA",
      "confidence": 0.9643
    },
    {
      "text": "BORONG PINTAR SDN BHD",
      "confidence": 0.9329
    }
  ]
}